RockPaperScissorsFullGame/ML.py
RockPaperScissorsFullGame/RPS.py
RockPaperScissorsFullGame/__init__.py
RockPaperScissorsFullGame/__main__.py
RockPaperScissorsFullGame-1.2.8.dist-info/LICENSE
RockPaperScissorsFullGame-1.2.8.dist-info/METADATA
RockPaperScissorsFullGame-1.2.8.dist-info/WHEEL
RockPaperScissorsFullGame-1.2.8.dist-info/entry_points.txt
RockPaperScissorsFullGame-1.2.8.dist-info/top_level.txt
RockPaperScissorsFullGame-1.2.8.dist-info/RECORD
