Metadata-Version: 2.1
Name: RockPaperScissorsFullGame
Version: 1.2.8
Summary: A Rock Paper Scissor Game
Author: Team 6
License: GNU GENERAL PUBLIC LICENSE
Project-URL: Homepage, https://github.com/software-students-fall2022/python-package-exercise-project-3-team-6
Project-URL: Repository, https://github.com/software-students-fall2022/python-package-exercise-project-3-team-6.git
Project-URL: Bug Tracker, https://github.com/software-students-fall2022/python-package-exercise-project-3-team-6/issues
Keywords: game,rock,paper,scissor,RockPaperScissors
Classifier: Programming Language :: Python :: 3
Classifier: Intended Audience :: Education
Classifier: License :: OSI Approved :: GNU General Public License v3 (GPLv3)
Classifier: Operating System :: OS Independent
Requires-Python: >=3.7
License-File: LICENSE
